bitwarden_pyro/__init__.py
bitwarden_pyro/__main__.py
bitwarden_pyro/bwpyro.py
bitwarden_pyro/settings.py
bitwarden_pyro/controller/__init__.py
bitwarden_pyro/controller/autotype.py
bitwarden_pyro/controller/cache.py
bitwarden_pyro/controller/clipboard.py
bitwarden_pyro/controller/session.py
bitwarden_pyro/controller/vault.py
bitwarden_pyro/model/__init__.py
bitwarden_pyro/model/actions.py
bitwarden_pyro/resources/__init__.py
bitwarden_pyro/resources/config
bitwarden_pyro/resources/icon.svg
bitwarden_pyro/util/__init__.py
bitwarden_pyro/util/arguments.py
bitwarden_pyro/util/config.py
bitwarden_pyro/util/executable.py
bitwarden_pyro/util/formatter.py
bitwarden_pyro/util/logger.py
bitwarden_pyro/util/notify.py
bitwarden_pyro/view/__init__.py
bitwarden_pyro/view/rofi.py
bitwarden_pyro-1.0.0.dist-info/LICENSE
bitwarden_pyro-1.0.0.dist-info/METADATA
bitwarden_pyro-1.0.0.dist-info/WHEEL
bitwarden_pyro-1.0.0.dist-info/entry_points.txt
bitwarden_pyro-1.0.0.dist-info/top_level.txt
bitwarden_pyro-1.0.0.dist-info/RECORD
