Metadata-Version: 2.1
Name: bitwarden-pyro
Version: 1.0.0
Summary: Bitwarden python interface built with Rofi
Home-page: https://github.com/mihalea/bitwarden-pyro
Author: Mircea Mihalea
Author-email: mircea@mihalea.ro
License: MIT
Platform: UNKNOWN
Requires-Dist: pyyaml
